odoo_somconnexio_python_client/__init__.py
odoo_somconnexio_python_client/client.py
odoo_somconnexio_python_client/exceptions.py
odoo_somconnexio_python_client/helpers.py
odoo_somconnexio_python_client/resources/__init__.py
odoo_somconnexio_python_client/resources/address.py
odoo_somconnexio_python_client/resources/broadband_isp_info.py
odoo_somconnexio_python_client/resources/contract.py
odoo_somconnexio_python_client/resources/coop_agreement.py
odoo_somconnexio_python_client/resources/crm_lead.py
odoo_somconnexio_python_client/resources/crm_lead_line.py
odoo_somconnexio_python_client/resources/discovery_channel.py
odoo_somconnexio_python_client/resources/fiber_contracts.py
odoo_somconnexio_python_client/resources/invoice.py
odoo_somconnexio_python_client/resources/knowledge.py
odoo_somconnexio_python_client/resources/mobile_isp_info.py
odoo_somconnexio_python_client/resources/multimedia_contract.py
odoo_somconnexio_python_client/resources/odoo_paging.py
odoo_somconnexio_python_client/resources/one_shot_catalog.py
odoo_somconnexio_python_client/resources/partner.py
odoo_somconnexio_python_client/resources/product_catalog.py
odoo_somconnexio_python_client/resources/provider.py
odoo_somconnexio_python_client/resources/sponsees.py
odoo_somconnexio_python_client/resources/subscription_request.py
tests/resources/__init__.py
tests/resources/test_address.py
tests/resources/test_contract.py
tests/resources/test_coop_agreement.py
tests/resources/test_crm_lead.py
tests/resources/test_discovery_channel.py
tests/resources/test_fiber_contracts.py
tests/resources/test_invoice.py
tests/resources/test_knowledge.py
tests/resources/test_multimedia_contract.py
tests/resources/test_one_shot_catalog.py
tests/resources/test_partner.py
tests/resources/test_product_catalog.py
tests/resources/test_providers.py
tests/resources/test_subscription_request.py
odoo_somconnexio_python_client-0.1.49.dist-info/LICENSE
odoo_somconnexio_python_client-0.1.49.dist-info/METADATA
odoo_somconnexio_python_client-0.1.49.dist-info/WHEEL
odoo_somconnexio_python_client-0.1.49.dist-info/top_level.txt
odoo_somconnexio_python_client-0.1.49.dist-info/RECORD
