Metadata-Version: 2.1
Name: odoo-somconnexio-python-client
Version: 0.1.49
Summary: Python wrapper for SomConnexio's Odoo (using REST API)
Home-page: https://gitlab.com/coopdevs/odoo-somconnexio-python-client
Author: Coopdevs
Author-email: info@coopdevs.org
Maintainer: Daniel Palomar
License: UNKNOWN
Platform: UNKNOWN
Classifier: Development Status :: 3 - Alpha
Classifier: Operating System :: POSIX :: Linux
Classifier: Programming Language :: Python :: 2
Classifier: Programming Language :: Python :: 2.7
License-File: LICENSE
Requires-Dist: requests
